cleanpy/__init__.py
cleanpy/__main__.py
cleanpy/__version__.py
cleanpy/_const.py
cleanpy/_finder.py
cleanpy/_manipulator.py
cleanpy-0.5.1.dist-info/LICENSE
cleanpy-0.5.1.dist-info/METADATA
cleanpy-0.5.1.dist-info/WHEEL
cleanpy-0.5.1.dist-info/entry_points.txt
cleanpy-0.5.1.dist-info/top_level.txt
cleanpy-0.5.1.dist-info/RECORD
